sqlkite/__init__.py
sqlkite/orm/__init__.py
sqlkite/orm/base.py
sqlkite-0.1.0.dist-info/METADATA
sqlkite-0.1.0.dist-info/WHEEL
sqlkite-0.1.0.dist-info/entry_points.txt
sqlkite-0.1.0.dist-info/top_level.txt
sqlkite-0.1.0.dist-info/RECORD
