Metadata-Version: 2.1
Name: sqlkite
Version: 0.1.0
Summary: A research and development initiative for crafting a Python based ORM
Home-page: https://github.com/imamhossainroni/sqlkite
Author: Imam Hossain Roni
Author-email: imamhossainroni95@gmail.com
Project-URL: Bug Tracker, https://github.com/imamhossainroni/sqlkite/issues
Project-URL: Source Code, https://github.com/imamhossainroni/sqlkite
Project-URL: Documentation, https://github.com/imamhossainroni/sqlkite/blob/main/README.md
Keywords: sqlkite,orm,sql
Classifier: Development Status :: 3 - Alpha
Classifier: Intended Audience :: Developers
Classifier: License :: OSI Approved :: MIT License
Classifier: Programming Language :: Python :: 3
Classifier: Programming Language :: Python :: 3.7
Classifier: Programming Language :: Python :: 3.8
Classifier: Programming Language :: Python :: 3.9
Classifier: Topic :: Internet :: WWW/HTTP
Classifier: Topic :: Software Development :: Libraries :: Python Modules
